pyroscopegridding/__init__.py
pyroscopegridding/fileparser.py
pyroscopegridding/filter_data.py
pyroscopegridding/grid_ncf.py
pyroscopegridding/gridding.py
pyroscopegridding/gtools.py
pyroscopegridding/naming_conventions.py
pyroscopegridding/sat_data_input.py
pyroscopegridding/solar_zenith.py
pyroscopegridding/time_conv.py
pyroscopegridding-0.3.1.6.dist-info/LICENSE.txt
pyroscopegridding-0.3.1.6.dist-info/METADATA
pyroscopegridding-0.3.1.6.dist-info/WHEEL
pyroscopegridding-0.3.1.6.dist-info/entry_points.txt
pyroscopegridding-0.3.1.6.dist-info/top_level.txt
pyroscopegridding-0.3.1.6.dist-info/RECORD
