Metadata-Version: 2.1
Name: pyroscopegridding
Version: 0.3.1.6
Summary: Data fusion package for transforming L2 satellite to L3 spatial-temporal gridded data
Home-page: https://github.com/jwei-openscapes/aerosol-data-fusion
Author: Sally Zhao, Neil Gutkin
Author-email: zhaosally0@gmail.com
License: MIT
Keywords: data fusion,satellite,L2,L3
Platform: UNKNOWN
Classifier: Development Status :: 3 - Alpha
Classifier: Intended Audience :: Developers
Classifier: Topic :: Software Development :: Build Tools
Classifier: License :: OSI Approved :: MIT License
Classifier: Programming Language :: Python :: 3
Classifier: Programming Language :: Python :: 3.4
Classifier: Programming Language :: Python :: 3.5
Classifier: Programming Language :: Python :: 3.6
Requires-Dist: argparse
Requires-Dist: joblib
Requires-Dist: netCDF4
Requires-Dist: numba
Requires-Dist: numpy
Requires-Dist: pandas
Requires-Dist: pyhdf
Requires-Dist: pyyaml
